Metadata-Version: 2.1
Name: image3d
Version: 0.1.0
Summary: 在python中基于OpenGL封装的三维可视化库
Home-page: https://github.com/hai2007/image3D.py
Author: hai2007
Author-email: 2501482523@qq.com
License: MIT
Classifier: Programming Language :: Python :: 3
Classifier: License :: OSI Approved :: MIT License
Classifier: Operating System :: OS Independent
License-File: LICENSE
License-File: AUTHORS.txt
